data_persistence_repository/__init__.py
data_persistence_repository/repository_interface.py
data_persistence_repository/sql_repository.py
data_persistence_repository/sql_repository_async.py
data_persistence_repository-0.2.3.dist-info/LICENSE
data_persistence_repository-0.2.3.dist-info/METADATA
data_persistence_repository-0.2.3.dist-info/WHEEL
data_persistence_repository-0.2.3.dist-info/top_level.txt
data_persistence_repository-0.2.3.dist-info/RECORD
