Metadata-Version: 2.1
Name: data-persistence-repository
Version: 0.2.3
Summary: A repository implementation for data persistence.
Home-page: https://github.com/smileservices/data_persistence_repository
Author: vladimir gorea
Author-email: vladimir@smileservices.dev
Classifier: Programming Language :: Python :: 3
Classifier: License :: OSI Approved :: MIT License
Classifier: Operating System :: OS Independent
Requires-Python: >=3.6
License-File: LICENSE
Requires-Dist: exceptiongroup ==1.2.0
Requires-Dist: greenlet >=3.0.0
Requires-Dist: iniconfig >=2.0.0
Requires-Dist: pluggy
Requires-Dist: psycopg2 >=2.9.9
Requires-Dist: SQLAlchemy >=2.0.0
Requires-Dist: SQLAlchemy-Utils >=0.41
Requires-Dist: tomli >=2.0.0
Requires-Dist: typing-extensions >=4.9.0
Requires-Dist: asyncpg >=0.29.0
